cchecksum-0.4.1.dist-info/RECORD
cchecksum-0.4.1.dist-info/WHEEL
cchecksum-0.4.1.dist-info/top_level.txt
cchecksum-0.4.1.dist-info/METADATA
cchecksum-0.4.1.dist-info/licenses/LICENSE
cchecksum/keccak.c
cchecksum/_checksum.pyi
cchecksum/__init__.py
cchecksum/_checksum.c
cchecksum/monkey_patch.py
cchecksum/_checksum.cpython-313-darwin.so
cchecksum/_checksum.pyx
cchecksum/keccak.h
cchecksum/py.typed
benchmarks/test_checksum_benchmarks.py
benchmarks/__init__.py
benchmarks/data.py
